todo_list_mcp/__init__.py
todo_list_mcp/assets/__init__.py
todo_list_mcp/assets/reminder_chime.wav
todo_list_mcp/github_file_client.py
todo_list_mcp/logging_config.py
todo_list_mcp/mcp_server.py
todo_list_mcp/models.py
todo_list_mcp/reminder_cli.py
todo_list_mcp/settings.py
todo_list_mcp/sound_client.py
todo_list_mcp/sqlite_client.py
todo_list_mcp/tkinter_reminder_client.py
todo_list_mcp/wxpython_reminder_client.py
todo_list_mcp-0.3.1.dist-info/WHEEL
todo_list_mcp-0.3.1.dist-info/entry_points.txt
todo_list_mcp-0.3.1.dist-info/METADATA
todo_list_mcp-0.3.1.dist-info/RECORD
