Metadata-Version: 2.3
Name: todo-list-mcp
Version: 0.3.1
Summary: Add your description here
Keywords: mcp,model-context-protocol,developer-tools,fastmcp
Author: l0kifs
Author-email: l0kifs <l0kifs91@gmail.com>
License: MIT
Classifier: Development Status :: 3 - Alpha
Classifier: Intended Audience :: Developers
Classifier: License :: OSI Approved :: MIT License
Classifier: Operating System :: OS Independent
Classifier: Operating System :: Microsoft :: Windows
Classifier: Operating System :: MacOS
Classifier: Operating System :: POSIX :: Linux
Classifier: Programming Language :: Python :: 3
Classifier: Programming Language :: Python :: 3.12
Classifier: Programming Language :: Python :: 3.13
Classifier: Topic :: Software Development :: Libraries :: Python Modules
Classifier: Environment :: Plugins
Classifier: Natural Language :: English
Requires-Dist: fastmcp>=2.14.2
Requires-Dist: pydantic>=2.11.7
Requires-Dist: httpx>=0.28.1
Requires-Dist: sqlalchemy>=2.0.0
Requires-Dist: typer>=0.21.1
Requires-Dist: rich>=14.2.0
Requires-Dist: loguru>=0.7.3
Requires-Dist: pydantic-settings>=2.12.0
Requires-Dist: wxpython>=4.2.0
Maintainer: l0kifs
Maintainer-email: l0kifs <l0kifs91@gmail.com>
Requires-Python: >=3.11
Project-URL: Homepage, https://github.com/l0kifs/todo-list-mcp
Project-URL: Documentation, https://github.com/l0kifs/todo-list-mcp/blob/main/README.md
Project-URL: Repository, https://github.com/l0kifs/todo-list-mcp.git
Project-URL: Issues, https://github.com/l0kifs/todo-list-mcp/issues
Project-URL: Changelog, https://github.com/l0kifs/todo-list-mcp/blob/main/CHANGELOG.md
